cv_data
